osm2geojson/__init__.py
osm2geojson/__main__.py
osm2geojson/areaKeys.json
osm2geojson/helpers.py
osm2geojson/main.py
osm2geojson/parse_xml.py
osm2geojson/polygon-features.json
osm2geojson-0.3.0.dist-info/licenses/LICENSE
osm2geojson-0.3.0.dist-info/METADATA
osm2geojson-0.3.0.dist-info/WHEEL
osm2geojson-0.3.0.dist-info/entry_points.txt
osm2geojson-0.3.0.dist-info/top_level.txt
osm2geojson-0.3.0.dist-info/RECORD
