Metadata-Version: 2.4
Name: osm2geojson
Version: 0.3.0
Summary: Parse OSM and Overpass JSON
Author-email: Parfeniuk Mykola <mikola.parfenyuck@gmail.com>
License: MIT
Project-URL: Homepage, https://github.com/aspectumapp/osm2geojson
Project-URL: Repository, https://github.com/aspectumapp/osm2geojson
Project-URL: Issues, https://github.com/aspectumapp/osm2geojson/issues
Keywords: geometry,gis,osm,parsing
Classifier: Development Status :: 4 - Beta
Classifier: Intended Audience :: Developers
Classifier: Programming Language :: Python :: 3
Classifier: Programming Language :: Python :: 3.8
Classifier: Programming Language :: Python :: 3.9
Classifier: Programming Language :: Python :: 3.10
Classifier: Programming Language :: Python :: 3.11
Classifier: Programming Language :: Python :: 3.12
Classifier: Programming Language :: Python :: 3.13
Classifier: Topic :: Software Development :: Libraries :: Python Modules
Classifier: Topic :: Scientific/Engineering :: GIS
Requires-Python: >=3.8
License-File: LICENSE
Requires-Dist: shapely>=2.0.0
Requires-Dist: requests>=2.25.0
Provides-Extra: dev
Requires-Dist: pytest>=7.4.0; extra == "dev"
Requires-Dist: pytest-cov>=4.1.0; extra == "dev"
Requires-Dist: black>=23.7.0; extra == "dev"
Requires-Dist: ruff>=0.1.0; extra == "dev"
Requires-Dist: mypy>=1.5.0; extra == "dev"
Requires-Dist: pre-commit>=3.3.0; extra == "dev"
Dynamic: license-file
